setup.py
gust/__init__.py
gust.egg-info/PKG-INFO
gust.egg-info/SOURCES.txt
gust.egg-info/dependency_links.txt
gust.egg-info/requires.txt
gust.egg-info/top_level.txt
gust/core/__init__.py
gust/core/datamodel_pb2.py