Metadata-Version: 1.1
Name: gust
Version: 1.0.2
Summary: Gust shim for Python.
Home-page: https://github.com/sgammon/GUST
Author: Sam Gammon
Author-email: sam.g@cookies.co
License: UNKNOWN
Platform: UNKNOWN
Requires: protobuf
